analisis_datos_examen/__init__.py
analisis_datos_examen/core.py
analisis_datos_examen_tu_nombre-0.1.0.dist-info/METADATA
analisis_datos_examen_tu_nombre-0.1.0.dist-info/WHEEL
analisis_datos_examen_tu_nombre-0.1.0.dist-info/top_level.txt
analisis_datos_examen_tu_nombre-0.1.0.dist-info/RECORD
