Metadata-Version: 2.4
Name: analisis_datos_examen_tu_nombre
Version: 0.1.0
Summary: Librería para el examen de análisis de datos
Author-email: Tu Nombre <tu.email@mondragon.edu>
License: MIT
Project-URL: Homepage, https://github.com/aimarsm/analisis_datos_examen
Keywords: analisis,pandas,examen
Classifier: Programming Language :: Python :: 3
Classifier: License :: OSI Approved :: MIT License
Classifier: Operating System :: OS Independent
Requires-Python: >=3.8
Requires-Dist: pandas
Requires-Dist: numpy
Requires-Dist: matplotlib
Requires-Dist: seaborn
